serverPKI/__init__.py
serverPKI/_version.py
serverPKI/cacert.py
serverPKI/cert.py
serverPKI/certdist.py
serverPKI/db.py
serverPKI/issue_LE.py
serverPKI/issue_local.py
serverPKI/operate.py
serverPKI/schedule.py
serverPKI/settrace.py
serverPKI/settrace_example.py
serverPKI/utils.py
serverPKI-0.9.11.data/data/share/doc/serverPKI/ERD.pdf
serverPKI-0.9.11.data/data/share/doc/serverPKI/States.pdf
serverPKI-0.9.11.data/data/share/serverPKI/example_config.conf
serverPKI-0.9.11.data/data/share/serverPKI/db/README
serverPKI-0.9.11.data/data/share/serverPKI/db/create_extension_citext.sql
serverPKI-0.9.11.data/data/share/serverPKI/db/create_schema_dd.sql
serverPKI-0.9.11.data/data/share/serverPKI/db/create_schema_pki.sql
serverPKI-0.9.11.data/data/share/serverPKI/db/create_triggers_pki.sql
serverPKI-0.9.11.data/data/share/serverPKI/db/load_services.sql
serverPKI-0.9.11.data/data/share/serverPKI/db/load_testdata.sql
serverPKI-0.9.11.data/data/share/serverPKI/db/upgrade_to_2.sql
serverPKI-0.9.11.data/data/share/serverPKI/db/upgrade_to_3.sql
serverPKI-0.9.11.data/data/share/serverPKI/db/upgrade_to_4.sql
serverPKI-0.9.11.data/data/share/serverPKI/db/upgrade_to_5.sql
serverPKI-0.9.11.data/data/share/serverPKI/db/upgrade_to_6.sql
serverPKI-0.9.11.dist-info/LICENSE.txt
serverPKI-0.9.11.dist-info/METADATA
serverPKI-0.9.11.dist-info/WHEEL
serverPKI-0.9.11.dist-info/entry_points.txt
serverPKI-0.9.11.dist-info/top_level.txt
serverPKI-0.9.11.dist-info/RECORD
