Metadata-Version: 2.1
Name: serverPKI
Version: 0.9.11
Summary: PKI for internet server infrastructure
Home-page: https://serverpki.readthedocs.io
Author: Axel Rau
Author-email: Axel.Rau@Chaos1.DE
License: GPLv3
Platform: UNKNOWN
Classifier: Development Status :: 5 - Production/Stable
Classifier: Environment :: Console
Classifier: Intended Audience :: System Administrators
Classifier: License :: OSI Approved :: GNU General Public License (GPL)
Classifier: Operating System :: POSIX
Classifier: Operating System :: MacOS :: MacOS X
Classifier: Topic :: Internet
Classifier: Topic :: Security :: Cryptography
Classifier: Programming Language :: Python :: 3
Classifier: Programming Language :: Python :: 3 :: Only
Classifier: Programming Language :: Python :: 3.7
Classifier: Programming Language :: Python :: 3.8
Classifier: Natural Language :: English
Requires-Dist: automatoes (>=0.9.5)
Requires-Dist: configobj (>=5.0.6)
Requires-Dist: cryptography (>=2.9.2)
Requires-Dist: dnspython (>=1.16.0)
Requires-Dist: py-postgresql (>=1.2.1)
Requires-Dist: paramiko (>=2.4.2)
Requires-Dist: prettytable (>=0.7.2)
Requires-Dist: iso8601
